{
  "coordinates": {
    "left_shoulder": {
      "x": 0.6135544776916504, 
      "y": 0.1931537538766861
    }, 
    "right_shoulder": {
      "x": 0.48983725905418396, 
      "y": 0.18909142911434174
    }, 
    "left_elbow": {
      "x": 0.6980249285697937, 
      "y": 0.21066221594810486
    }, 
    "right_elbow": {
      "x": 0.4069509506225586, 
      "y": 0.2103276252746582
    }, 
    "left_wrist": {
      "x": 0.780503511428833, 
      "y": 0.20233546197414398
    }, 
    "right_wrist": {
      "x": 0.31629496812820435, 
      "y": 0.18803729116916656
    }, 
    "left_hip": {
      "x": 0.57740318775177, 
      "y": 0.4484754204750061
    }, 
    "right_hip": {
      "x": 0.5086852312088013, 
      "y": 0.4472084939479828
    }, 
    "left_knee": {
      "x": 0.6029209494590759, 
      "y": 0.6410442590713501
    }, 
    "right_knee": {
      "x": 0.4808199405670166, 
      "y": 0.6377374529838562
    }, 
    "left_ankle": {
      "x": 0.6365550756454468, 
      "y": 0.843950092792511
    }, 
    "right_ankle": {
      "x": 0.4518950879573822, 
      "y": 0.8385148644447327
    }
  }, 
  "landmarks": {
    "left_shoulder": 11, 
    "right_shoulder": 12, 
    "left_elbow": 13, 
    "right_elbow": 14, 
    "left_wrist": 15, 
    "right_wrist": 16, 
    "left_hip": 23, 
    "right_hip": 24, 
    "left_knee": 25, 
    "right_knee": 26, 
    "left_ankle": 27, 
    "right_ankle": 28
  }, 
  "connections": [
    [
      "left_shoulder", 
      "left_elbow"
    ], 
    [
      "left_elbow", 
      "left_wrist"
    ], 
    [
      "right_shoulder", 
      "right_elbow"
    ], 
    [
      "right_elbow", 
      "right_wrist"
    ], 
    [
      "left_hip", 
      "left_knee"
    ], 
    [
      "right_hip", 
      "right_knee"
    ], 
    [
      "left_knee", 
      "left_ankle"
    ], 
    [
      "right_knee", 
      "right_ankle"
    ], 
    [
      "left_shoulder", 
      "left_hip"
    ], 
    [
      "right_shoulder", 
      "right_hip"
    ]
  ]
}